continuousvi/__init__.py
continuousvi/continuousVI.py
continuousvi/continuous_harmony.py
continuousvi/simulation.py
continuousvi/trajectory.py
continuousvi-0.1.12.dist-info/METADATA
continuousvi-0.1.12.dist-info/WHEEL
continuousvi-0.1.12.dist-info/entry_points.txt
continuousvi-0.1.12.dist-info/RECORD
