Metadata-Version: 2.4
Name: continuousvi
Version: 0.1.12
Summary: Analyzing single-cell RNA-seq data with continuous covariates extinding scVI.
Author-email: Yuya Sato <yu.pisces.556223@akane.waseda.jp>
Requires-Python: >=3.10
Requires-Dist: anndata==0.11
Requires-Dist: fa2-modified>=0.3.10
Requires-Dist: grandprix>=0.1.2
Requires-Dist: igraph>=0.11.8
Requires-Dist: leidenalg>=0.10.2
Requires-Dist: numpy>=2.0.2
Requires-Dist: openpyxl>=3.1.5
Requires-Dist: pandas>=2.2.3
Requires-Dist: patsy>=1.0.1
Requires-Dist: polars>=1.26.0
Requires-Dist: pyarrow>=19.0.1
Requires-Dist: pygam>=0.8.0
Requires-Dist: requests>=2.32.3
Requires-Dist: scanpy>=1.8.0
Requires-Dist: scvi-tools>=1.3.0
Requires-Dist: statsmodels>=0.14.4
Requires-Dist: torch==2.5.1
